{
 "@search.score": 1.0,
 "canUserModifySchedule": true,
 "isCapacityControlled": false,
 "roomHasCapacity": true,
 "rsvpOpensAt": "2020-02-10T02:00:00+00:00",
 "hasRsvpOpened": true,
 "hasRsvpClosed": false,
 "waitlistHasCapacity": true,
 "capacity": 234,
 "attendeeCount": 34,
 "sessionId": "90709",
 "sessionInstanceId": "90709",
 "sessionCode": "BRK20003",
 "sessionCodeNormalized": "BRK20003",
 "title": "Outlook mobile: The gold standard for secure communications in the enterprise.",
 "sortTitle": "outlook mobile: the gold standard for secure communications in the enterprise.",
 "sortRank": 2147483647,
 "description": "Outlook for iOS and Android helps separate work and personal data, even without device enrollment! Keep your users happy and productive while seamlessly managing how data can move between applications. There is no better client for managing your enterprise email data.",
 "registrationLink": "",
 "roomId": "",
 "location": "Sheikh Rashid Hall A",
 "buildingLocation": "",
 "startDateTime": "2020-02-10T08:15:00+00:00",
 "endDateTime": "2020-02-10T09:00:00+00:00",
 "durationInMinutes": 45,
 "sessionType": "Breakout: 45 Minute",
 "sessionTypeLogical": "Breakout: 45 Minute",
 "learningPath": "",
 "level": "",
 "products": [],
 "format": "",
 "topic": "",
 "sessionTypeId": "3106",
 "slideDeck": "",
 "isMandatory": false,
 "visibleToAnonymousUsers": true,
 "visibleInSessionListing": true,
 "canBeEvaluated": true,
 "liveStream": "",
 "onDemand": "",
 "downloadVideoLink": "",
 "translatorLink": "https://aka.ms/IBO8",
 "onDemandThumbnail": "",
 "techCommunityDiscussionId": "",
 "speakerIds": [
  "697460"
 ],
 "speakerNames": [
  "Mohamed Marzouk"
 ],
 "speakerCompanies": [
  "Microsoft"
 ],
 "sessionSets": [
  "Session Catalog 2019",
  "Session Scheduler",
  "My Schedule"
 ],
 "sessionLinks": [],
 "marketingCampaign": [],
 "overflowStatus": "",
 "links": "",
 "waitlistCapacity": 2147483647,
 "waitlistCount": 0,
 "lastUpdate": "2020-02-10T03:15:14.53+00:00",
 "techCommunityUrl": "",
 "overflowRooms": [],
 "childModules": [],
 "siblingModules": []
}