{
 "@search.score": 1.0,
 "canUserModifySchedule": true,
 "isCapacityControlled": true,
 "roomHasCapacity": true,
 "rsvpOpensAt": "2019-10-02T14:00:00+00:00",
 "hasRsvpOpened": true,
 "hasRsvpClosed": false,
 "waitlistHasCapacity": true,
 "capacity": 90,
 "attendeeCount": 49,
 "sessionId": "95087",
 "sessionInstanceId": "95087",
 "sessionCode": "UNC10050",
 "sessionCodeNormalized": "UNC10050",
 "title": "Real-time streaming with Power BI",
 "sortTitle": "real-time streaming with power bi",
 "sortRank": 2147483647,
 "description": "Developers have a superpower: they know how JSON works. Use this knowledge to feed real-time streaming into Power BI. Learn how this powerful visualization is different from the others and how it can be used in your organization.",
 "registrationLink": "",
 "roomId": "",
 "location": "Theater 3",
 "buildingLocation": "",
 "startDateTime": "2020-02-10T10:50:00+00:00",
 "endDateTime": "2020-02-10T12:00:00+00:00",
 "durationInMinutes": 70,
 "sessionType": "Unconference: 70 Minute",
 "sessionTypeLogical": "Unconference: 70 Minute",
 "learningPath": "",
 "level": "",
 "products": [],
 "format": "",
 "topic": "",
 "sessionTypeId": "3111",
 "slideDeck": "",
 "isMandatory": false,
 "visibleToAnonymousUsers": true,
 "visibleInSessionListing": true,
 "canBeEvaluated": true,
 "liveStream": "",
 "onDemand": "",
 "downloadVideoLink": "",
 "translatorLink": "https://aka.ms/ITR3",
 "onDemandThumbnail": "",
 "techCommunityDiscussionId": "",
 "speakerIds": [
  "766996"
 ],
 "speakerNames": [
  "Mohammed Owais"
 ],
 "speakerCompanies": [
  "PwC"
 ],
 "sessionSets": [
  "Session Catalog 2019",
  "Session Scheduler",
  "My Schedule"
 ],
 "sessionLinks": [],
 "marketingCampaign": [],
 "overflowStatus": "",
 "links": "",
 "waitlistCapacity": 2,
 "waitlistCount": 0,
 "lastUpdate": "2020-02-10T03:15:14.53+00:00",
 "techCommunityUrl": "",
 "overflowRooms": [],
 "childModules": [],
 "siblingModules": []
}